README.txt
setup.py
PyWare.egg-info/PKG-INFO
PyWare.egg-info/SOURCES.txt
PyWare.egg-info/dependency_links.txt
PyWare.egg-info/requires.txt
PyWare.egg-info/top_level.txt
pyware/__init__.py