Metadata-Version: 2.1
Name: PyWare
Version: 0.0.2
Summary: Package for ease of access to game hacking
Home-page: https://kiy.rip/
Author: Geek
Author-email: gaminggeekeh@gmail.com
